quartet_integrations/__init__.py
quartet_integrations/apps.py
quartet_integrations/models.py
quartet_integrations/urls.py
quartet_integrations/views.py
quartet_integrations/divinci/__init__.py
quartet_integrations/divinci/parsing.py
quartet_integrations/divinci/steps.py
quartet_integrations/extended/__init__.py
quartet_integrations/extended/environment.py
quartet_integrations/extended/events.py
quartet_integrations/extended/parsers.py
quartet_integrations/extended/steps.py
quartet_integrations/frequentz/__init__.py
quartet_integrations/frequentz/environment.py
quartet_integrations/frequentz/parsers.py
quartet_integrations/frequentz/steps.py
quartet_integrations/generic/__init__.py
quartet_integrations/generic/mixins.py
quartet_integrations/generic/parsing.py
quartet_integrations/generic/steps.py
quartet_integrations/generic/urls.py
quartet_integrations/generic/views.py
quartet_integrations/gs1ushc/__init__.py
quartet_integrations/gs1ushc/mixins.py
quartet_integrations/gs1ushc/parsing.py
quartet_integrations/gs1ushc/steps.py
quartet_integrations/management/__init__.py
quartet_integrations/management/commands/__init__.py
quartet_integrations/management/commands/create_extended_shipping_rule.py
quartet_integrations/management/commands/create_external_response_rules.py
quartet_integrations/management/commands/create_opsm_filter.py
quartet_integrations/management/commands/create_opsm_gtin_range.py
quartet_integrations/management/commands/create_opsm_sscc_range.py
quartet_integrations/management/commands/create_optel_templates.py
quartet_integrations/management/commands/create_oracle_import_rule.py
quartet_integrations/management/commands/create_serialbox_urn_response_rule.py
quartet_integrations/management/commands/create_systech_templates.py
quartet_integrations/management/commands/load_gs1ushc_output_rules.py
quartet_integrations/management/commands/utils.py
quartet_integrations/mmd/__init__.py
quartet_integrations/mmd/exceptions.py
quartet_integrations/mmd/parsing.py
quartet_integrations-10.0.0.dist-info/AUTHORS.rst
quartet_integrations-10.0.0.dist-info/LICENSE
quartet_integrations-10.0.0.dist-info/METADATA
quartet_integrations-10.0.0.dist-info/WHEEL
quartet_integrations-10.0.0.dist-info/top_level.txt
quartet_integrations-10.0.0.dist-info/RECORD
