Metadata-Version: 2.1
Name: quartet-integrations
Version: 10.0.0
Summary: Third party integrations for the QU4RTET platform.
Home-page: https://gitlab.com/serial-lab/quartet_integrations
Author: SerialLab, Corp
Author-email: slab@serial-lab.com
License: GPLv3
Keywords: quartet_integrations
Platform: UNKNOWN
Classifier: Development Status :: 5 - Production/Stable
Classifier: Intended Audience :: Developers
Classifier: License :: OSI Approved :: GNU General Public License v3 (GPLv3)
Classifier: Natural Language :: English
Classifier: Programming Language :: Python :: 3.5
Classifier: Programming Language :: Python :: 3.6
